{
	"$schema" : "https://aka.ms/winget-packages.schema.2.0.json",
	"CreationDate" : "2021-09-04T21:45:43.045-00:00",
	"Sources" : 
	[
		{
			"Packages" : 
			[
				{
					"PackageIdentifier" : "agalwood.Motrix"
				},
				{
					"PackageIdentifier" : "ShareX.ShareX"
				},
				{
					"PackageIdentifier" : "AnyDeskSoftwareGmbH.AnyDesk"
				},
				{
					"PackageIdentifier" : "Audacity.Audacity"
				},
				{
					"PackageIdentifier" : "TGRMNSoftware.BulkRenameUtility"
				},
				{
					"PackageIdentifier" : "Canonical.Ubuntu"
				},
				{
					"PackageIdentifier" : "Discord.Discord"
				},
				{
					"PackageIdentifier" : "Mozilla.FirefoxDeveloperEdition"
				},
				{
					"PackageIdentifier" : "GitHub.GitHubDesktop"
				},
				{
					"PackageIdentifier" : "Git.Git"
				},
				{
					"PackageIdentifier" : "Google.Chrome.Beta"
				},
				{
					"PackageIdentifier" : "KDE.Kate"
				},
				{
					"PackageIdentifier" : "Microsoft.Edge"
				},
				{
					"PackageIdentifier" : "Microsoft.EdgeWebView2Runtime"
				},
				{
					"PackageIdentifier" : "Microsoft.WindowsTerminal"
				},
				{
					"PackageIdentifier" : "Notepad++.Notepad++"
				},
				{
					"PackageIdentifier" : "Opera.Opera"
				},
				{
					"PackageIdentifier" : "Daum.PotPlayer"
				},
				{
					"PackageIdentifier" : "Microsoft.Skype"
				},
				{
					"PackageIdentifier" : "Spotify.Spotify"
				},
				{
					"PackageIdentifier" : "Valve.Steam"
				},
				{
					"PackageIdentifier" : "TeamViewer.TeamViewer"
				},
				{
					"PackageIdentifier" : "JetBrains.Toolbox"
				},
				{
					"PackageIdentifier" : "JAMSoftware.TreeSizeFree"
				},
				{
					"PackageIdentifier" : "Caprine.Caprine"
				},
				{
					"PackageIdentifier" : "Notion.Notion"
				},
				{
					"PackageIdentifier" : "KDE.Kdenlive"
				},
				{
					"PackageIdentifier" : "qBittorrent.qBittorrent"
				},
				{
					"PackageIdentifier" : "HandyOrg.HandyWinget-GUI"
				},
				{
					"PackageIdentifier" : "Microsoft.VC++2013Redist-x64"
				},
				{
					"PackageIdentifier" : "alcpu.CoreTemp"
				},
				{
					"PackageIdentifier" : "Python.Python.3"
				},
				{
					"PackageIdentifier" : "VideoLAN.VLC"
				},
				{
					"PackageIdentifier" : "Microsoft.VC++2010Redist-x64"
				},
				{
					"PackageIdentifier" : "Microsoft.VisualStudioCode.Insiders"
				},
				{
					"PackageIdentifier" : "Microsoft.VC++2015-2019Redist-x64"
				},
				{
					"PackageIdentifier" : "Toinane.Colorpicker"
				},
				{
					"PackageIdentifier" : "Google.Chrome"
				},
				{
					"PackageIdentifier" : "Microsoft.dotnetRuntime.5-x86"
				},
				{
					"PackageIdentifier" : "Microsoft.VC++2015-2019Redist-x86"
				},
				{
					"PackageIdentifier" : "Telegram.TelegramDesktop"
				},
				{
					"PackageIdentifier" : "DuongDieuPhap.ImageGlass"
				},
				{
					"PackageIdentifier" : "Giorgiotani.Peazip"
				},
				{
					"PackageIdentifier" : "Microsoft.VC++2008Redist-x64"
				},
				{
					"PackageIdentifier" : "Microsoft.dotnetRuntime.5-x64"
				},
				{
					"PackageIdentifier" : "Microsoft.VC++2005Redist-x86"
				},
				{
					"PackageIdentifier" : "Microsoft.VC++2008Redist-x86"
				},
				{
					"PackageIdentifier" : "GitHub.cli"
				},
				{
					"PackageIdentifier" : "Microsoft.VC++2013Redist-x86"
				},
				{
					"PackageIdentifier" : "Meld.Meld"
				},
				{
					"PackageIdentifier" : "Microsoft.PowerToys"
				},
				{
					"PackageIdentifier" : "Microsoft.VC++2005Redist-x64"
				}
			],
			"SourceDetails" : 
			{
				"Argument" : "https://winget.azureedge.net/cache",
				"Identifier" : "Microsoft.Winget.Source_8wekyb3d8bbwe",
				"Name" : "winget",
				"Type" : "Microsoft.PreIndexed.Package"
			}
		}
	],
	"WinGetVersion" : "1.0.11692"
}